dis_inference/__about__.py
dis_inference/__init__.py
dis_inference/__main__.py
dis_inference/cli/__init__.py
dis_inference/models/__init__.py
dis_inference/models/isnet.py
dis_inference-1.1.3.dist-info/METADATA
dis_inference-1.1.3.dist-info/WHEEL
dis_inference-1.1.3.dist-info/entry_points.txt
dis_inference-1.1.3.dist-info/licenses/LICENSE.txt
dis_inference-1.1.3.dist-info/RECORD
