Metadata-Version: 2.1
Name: dis-inference
Version: 1.1.3
Summary: Inference implementation for Dichotomous Image Segmentation
Project-URL: Documentation, https://github.com/unknown/dis-inference#readme
Project-URL: Issues, https://github.com/unknown/dis-inference/issues
Project-URL: Source, https://github.com/unknown/dis-inference
Author-email: dh031200 <imbird0312@gmail.com>
License-Expression: AGPL-3.0-only
License-File: LICENSE.txt
Classifier: Development Status :: 4 - Beta
Classifier: Programming Language :: Python
Classifier: Programming Language :: Python :: 3.7
Classifier: Programming Language :: Python :: 3.8
Classifier: Programming Language :: Python :: 3.9
Classifier: Programming Language :: Python :: 3.10
Classifier: Programming Language :: Python :: 3.11
Classifier: Programming Language :: Python :: Implementation :: CPython
Classifier: Programming Language :: Python :: Implementation :: PyPy
Requires-Python: >=3.7
Requires-Dist: click
Requires-Dist: gdown
Requires-Dist: numpy
Requires-Dist: opencv-python
Requires-Dist: pyyaml
Requires-Dist: torch
Requires-Dist: torchvision
